unicorn_eval/__init__.py
unicorn_eval/evaluate.py
unicorn_eval/helpers.py
unicorn_eval/io.py
unicorn_eval/memory_profiler.py
unicorn_eval/utils.py
unicorn_eval/adaptors/__init__.py
unicorn_eval/adaptors/base.py
unicorn_eval/adaptors/classification.py
unicorn_eval/adaptors/components.py
unicorn_eval/adaptors/detection.py
unicorn_eval/adaptors/patch_extraction.py
unicorn_eval/adaptors/reconstruct_prediction.py
unicorn_eval/adaptors/regression.py
unicorn_eval/adaptors/segmentation/__init__.py
unicorn_eval/adaptors/segmentation/data_handling.py
unicorn_eval/adaptors/segmentation/decoders.py
unicorn_eval/adaptors/segmentation/inference.py
unicorn_eval/adaptors/segmentation/training.py
unicorn_eval/adaptors/segmentation/aimhi_linear_upsample_conv3d/__init__.py
unicorn_eval/adaptors/segmentation/aimhi_linear_upsample_conv3d/v1/__init__.py
unicorn_eval/adaptors/segmentation/aimhi_linear_upsample_conv3d/v1/main.py
unicorn_eval/adaptors/segmentation/aimhi_linear_upsample_conv3d/v2/__init__.py
unicorn_eval/adaptors/segmentation/aimhi_linear_upsample_conv3d/v2/main.py
unicorn_eval/adaptors/segmentation/baseline_segmentation_upsampling/__init__.py
unicorn_eval/adaptors/segmentation/baseline_segmentation_upsampling/main.py
unicorn_eval/adaptors/segmentation/baseline_segmentation_upsampling_3d/__init__.py
unicorn_eval/adaptors/segmentation/baseline_segmentation_upsampling_3d/v1/__init__.py
unicorn_eval/adaptors/segmentation/baseline_segmentation_upsampling_3d/v1/main.py
unicorn_eval/adaptors/segmentation/baseline_segmentation_upsampling_3d/v2/__init__.py
unicorn_eval/adaptors/segmentation/baseline_segmentation_upsampling_3d/v2/main.py
unicorn_eval/adaptors/segmentation/baseline_segmentation_upsampling_3d/v2/training.py
unicorn_eval/adaptors/segmentation/mevis_conv_segmentation_3d/__init__.py
unicorn_eval/adaptors/segmentation/mevis_conv_segmentation_3d/v1/__init__.py
unicorn_eval/adaptors/segmentation/mevis_conv_segmentation_3d/v1/main.py
unicorn_eval/metrics/__init__.py
unicorn_eval-3.0.5.dist-info/licenses/LICENSE
unicorn_eval-3.0.5.dist-info/METADATA
unicorn_eval-3.0.5.dist-info/WHEEL
unicorn_eval-3.0.5.dist-info/entry_points.txt
unicorn_eval-3.0.5.dist-info/top_level.txt
unicorn_eval-3.0.5.dist-info/RECORD
