Metadata-Version: 2.4
Name: unicorn_eval
Version: 3.0.5
Summary: Evaluation and adaption method for the UNICORN Challenge
Home-page: https://github.com/DIAGNijmegen/unicorn_eval
Author: Joeran Bosma, Clément Grisi, Marina D`Amato, Luc Builtjes, Lena Philipp, Fennie van der Graaf, Judith Lefkes, Michelle Stegeman, Rianne Weber
Author-email: Clement.Grisi@radboudumc.nl
Project-URL: Bug Tracker, https://github.com/DIAGNijmegen/unicorn_eval/issues
Platform: unix
Platform: linux
Platform: osx
Platform: cygwin
Platform: win32
Classifier: Programming Language :: Python :: 3
Classifier: Programming Language :: Python :: 3 :: Only
Classifier: Programming Language :: Python :: 3.10
Classifier: Programming Language :: Python :: 3.11
Classifier: Programming Language :: Python :: 3.12
Classifier: Programming Language :: Python :: 3.13
Requires-Python: >=3.10
License-File: LICENSE
Requires-Dist: scikit-learn>=1.6.1
Requires-Dist: numpy==1.26.1
Requires-Dist: pandas
Requires-Dist: psutil
Requires-Dist: torch==2.0.1
Requires-Dist: torchvision==0.15.2
Requires-Dist: scikit-survival
Requires-Dist: pycocoevalcap
Requires-Dist: transformers==4.28.1
Requires-Dist: bert_score
Requires-Dist: evalutils==0.3.1
Requires-Dist: openslide-python
Requires-Dist: pycm
Provides-Extra: testing
Requires-Dist: pytest>=6.0; extra == "testing"
Requires-Dist: pytest-cov>=2.0; extra == "testing"
Requires-Dist: mypy>=0.910; extra == "testing"
Requires-Dist: flake8>=3.9; extra == "testing"
Requires-Dist: tox>=3.24; extra == "testing"
Dynamic: author-email
Dynamic: description
Dynamic: description-content-type
Dynamic: home-page
Dynamic: license-file
Dynamic: project-url
